Workbook

Sheet Data
A1: title | B1: vendor | C1: product_type | D1: price_min | E1: price_max | F1: compare_at_price | G1: on_sale | H1: available | I1: fully_out_of_stock | J1: variant_count | K1: url | L1: discount_pct
A2: Amazon Prime Day PR Kit | B2: blume-box | C2: Skin Care | D2: 175 | E2: 175 | G2: =FALSE() -> FALSE | H2: =TRUE() -> TRUE | I2: =FALSE() -> FALSE | J2: 1 | K2: https://meetblume.com/products/amazon-prime-day-pr-kit
A3: Blume's 8th Birthday PR Kit | B3: blume-box | C3: Skin Care | D3: 200 | E3: 200 | G3: =FALSE() -> FALSE | H3: =TRUE() -> TRUE | I3: =FALSE() -> FALSE | J3: 1 | K3: https://meetblume.com/products/blumes-8th-birthday-pr-kit
A4: Ulta Beauty PR Kit | B4: blume-box | C4: Skin Care | D4: 175 | E4: 175 | G4: =FALSE() -> FALSE | H4: =TRUE() -> TRUE | I4: =FALSE() -> FALSE | J4: 1 | K4: https://meetblume.com/products/ulta-beauty-pr-kit
A5: Blume's 8th Birthday Party: In Full Blume | B5: Blume | C5: Event | D5: 55 | E5: 55 | G5: =FALSE() -> FALSE | H5: =FALSE() -> FALSE | I5: =TRUE() -> TRUE | J5: 1 | K5: https://meetblume.com/products/blumes-8th-birthday-party-in-full-blume-at-the-gardens
A6: Clear Skin Kit PR Kit | B6: blume-box | C6: Skin Care | D6: 85 | E6: 85 | G6: =FALSE() -> FALSE | H6: =TRUE() -> TRUE | I6: =FALSE() -> FALSE | J6: 1 | K6: https://meetblume.com/products/glow-on-the-go-pr-kit
A7: Meltdown Daily Balancing Gel Cleanser | B7: blume-box | C7: Skin Care | D7: 86.4 | E7: 159.36 | F7: 192 | G7: =TRUE() -> TRUE | H7: =TRUE() -> TRUE | I7: =FALSE() -> FALSE | J7: 2 | K7: https://meetblume.com/products/meltdown-daily-balancing-gel-cleanser | L7: 55
A8: Blume Buddy Bag Charm Blind Box | B8: blume-box | C8: Skin Care | D8: 11 | E8: 11 | G8: =FALSE() -> FALSE | H8: =FALSE() -> FALSE | I8: =TRUE() -> TRUE | J8: 1 | K8: https://meetblume.com/products/blume-buddy-teddy-bear-bag-charm-blind-box
A9: Meltdown Acne Oil Treatment | B9: blume-box | C9: Unlisted | D9: 52 | E9: 179 | F9: 312 | G9: =TRUE() -> TRUE | H9: =TRUE() -> TRUE | I9: =FALSE() -> FALSE | J9: 3 | K9: https://meetblume.com/products/meltdown-acne-oil-7 | L9: 83.3
A10: Meltdown Acne Oil Treatment | B10: blume-box | C10: Unlisted | D10: 52 | E10: 52 | G10: =FALSE() -> FALSE | H10: =TRUE() -> TRUE | I10: =FALSE() -> FALSE | J10: 1 | K10: https://meetblume.com/products/meltdown-acne-oil-3
A11: Glow & Fade Kit | B11: Blume | C11: Bundle | D11: 66.4 | E11: 66.4 | F11: 83 | G11: =TRUE() -> TRUE | H11: =TRUE() -> TRUE | I11: =FALSE() -> FALSE | J11: 1 | K11: https://meetblume.com/products/glow-fade-kit | L11: 20
A12: Calming Hydration Kit | B12: Blume | C12: Bundle | D12: 51.2 | E12: 51.2 | F12: 64 | G12: =TRUE() -> TRUE | H12: =TRUE() -> TRUE | I12: =FALSE() -> FALSE | J12: 1 | K12: https://meetblume.com/products/calming-hydration-kit | L12: 20
A13: Glass Skin Kit | B13: Blume | C13: Bundle | D13: 88.8 | E13: 88.8 | F13: 111 | G13: =TRUE() -> TRUE | H13: =FALSE() -> FALSE | I13: =TRUE() -> TRUE | J13: 1 | K13: https://meetblume.com/products/glass-skin-kit | L13: 20
A14: Pearl Drip Soothing + Hydration Milky Toner | B14: blume-box | C14: Skin Care | D14: 36 | E14: 36 | G14: =FALSE() -> FALSE | H14: =TRUE() -> TRUE | I14: =FALSE() -> FALSE | J14: 1 | K14: https://meetblume.com/products/pearl-drip-hydration-and-calming-milky-toner
A15: Hydration Heroes Kit | B15: Blume | C15: Bundle | D15: 38.4 | E15: 38.4 | F15: 48 | G15: =TRUE() -> TRUE | H15: =FALSE() -> FALSE | I15: =TRUE() -> TRUE | J15: 1 | K15: https://meetblume.com/products/hydration-heroes-kit | L15: 20
A16: 24 Superbalm Bubblegum | B16: Blume | C16: Unlisted | D16: 480 | E16: 480 | G16: =FALSE() -> FALSE | H16: =TRUE() -> TRUE | I16: =FALSE() -> FALSE | J16: 1 | K16: https://meetblume.com/products/24-superbalm-bubblegum
A17: Fresh Face Edit | B17: Blume | C17: Bundle | D17: 55 | E17: 55 | F17: 79 | G17: =TRUE() -> TRUE | H17: =FALSE() -> FALSE | I17: =TRUE() -> TRUE | J17: 1 | K17: https://meetblume.com/products/fresh-face-edit | L17: 30.4
A18: The Ultimate Clear Skin Edit | B18: Blume | C18: Bundle | D18: 95 | E18: 95 | F18: 192 | G18: =TRUE() -> TRUE | H18: =TRUE() -> TRUE | I18: =FALSE() -> FALSE | J18: 1 | K18: https://meetblume.com/products/the-ultimate-clear-skin-edit | L18: 50.5
A19: Superbalm Tripeptide-1 Lip Tint in Wild Plum | B19: blume-box | C19: Skin Care | D19: 20 | E19: 20 | G19: =FALSE() -> FALSE | H19: =TRUE() -> TRUE | I19: =FALSE() -> FALSE | J19: 1 | K19: https://meetblume.com/products/superbalm-tripeptide-1-lip-tint-in-plum
A20: Blume Lip Balm Trio Kit | B20: Blume | C20: Bundle | D20: 40 | E20: 40 | F20: 60 | G20: =TRUE() -> TRUE | H20: =TRUE() -> TRUE | I20: =FALSE() -> FALSE | J20: 1 | K20: https://meetblume.com/products/superbalm-trio-kit-vanilla-toffee-plum | L20: 33.3
A21: Milky Fade Serum with Niacinamide for Spots & Scars | B21: blume-box | C21: Skin Care | D21: 47 | E21: 98 | F21: 141 | G21: =TRUE() -> TRUE | H21: =TRUE() -> TRUE | I21: =FALSE() -> FALSE | J21: 3 | K21: https://meetblume.com/products/milky-fade-serum-with-niacinamide-for-spots-scars | L21: 66.7
A22: Superbalm Tripeptide-1 Lip Tint in Bubblegum | B22: blume-box | C22: Skin Care | D22: 20 | E22: 20 | G22: =FALSE() -> FALSE | H22: =TRUE() -> TRUE | I22: =FALSE() -> FALSE | J22: 1 | K22: https://meetblume.com/products/superbalm-tripeptide-1-lip-tint-in-bubblegum
A23: Sunburst Mineral SPF 50 Sunscreen | B23: blume-box | C23: Skin Care | D23: 70 | E23: 96 | F23: 160 | G23: =TRUE() -> TRUE | H23: =TRUE() -> TRUE | I23: =FALSE() -> FALSE | J23: 3 | K23: https://meetblume.com/products/sunburst-mineral-spf-50-sunscreen | L23: 56.2
A24: Superbalm Tripeptide-1 Vanilla Lip Balm | B24: blume-box | C24: Skin Care | D24: 20 | E24: 20 | G24: =FALSE() -> FALSE | H24: =TRUE() -> TRUE | I24: =FALSE() -> FALSE | J24: 1 | K24: https://meetblume.com/products/superbalm-tripeptide-vanilla-lip-squeeze
A25: Superbalm Duo: Vanilla & Toffee | B25: Blume | C25: Bundle | D25: 36 | E25: 36 | F25: 40 | G25: =TRUE() -> TRUE | H25: =TRUE() -> TRUE | I25: =FALSE() -> FALSE | J25: 1 | K25: https://meetblume.com/products/superbalm-duo-vanilla-toffee | L25: 10
A26: Superbalm Tripeptide-1 Lip Tint in Toffee | B26: blume-box | C26: Skin Care | D26: 20 | E26: 20 | G26: =FALSE() -> FALSE | H26: =TRUE() -> TRUE | I26: =FALSE() -> FALSE | J26: 1 | K26: https://meetblume.com/products/superbalm-tripeptide-1-toffee-lip-tint
A27: Meltdown Gel Cream with Ceramides | B27: blume-box | C27: Skin Care | D27: 28 | E27: 110 | F27: 168 | G27: =TRUE() -> TRUE | H27: =TRUE() -> TRUE | I27: =FALSE() -> FALSE | J27: 3 | K27: https://meetblume.com/products/meltdown-gel-cream-with-ceramides | L27: 83.3
A28: Superbalm Tripeptide-1 Vanilla Lip Balm | B28: blume-box | C28: Skin Care | D28: 20 | E28: 20 | G28: =FALSE() -> FALSE | H28: =TRUE() -> TRUE | I28: =FALSE() -> FALSE | J28: 1 | K28: https://meetblume.com/products/superbalm
A29: Cloud 9 Cramp Oil | B29: blume-box | C29: Skin Care Rollers | D29: 20 | E29: 20 | G29: =FALSE() -> FALSE | H29: =TRUE() -> TRUE | I29: =FALSE() -> FALSE | J29: 1 | K29: https://meetblume.com/products/cloud9
A30: Sunburst Mineral SPF 50 Sunscreen | B30: blume-box | C30: Skin Care | D30: 40 | E30: 40 | G30: =FALSE() -> FALSE | H30: =TRUE() -> TRUE | I30: =FALSE() -> FALSE | J30: 1 | K30: https://meetblume.com/products/sunburst-mineral-spf-50
A31: Clear Skin Kit: Acne Essentials | B31: Blume | C31: Bundle | D31: 75 | E31: 75 | F31: 132 | G31: =TRUE() -> TRUE | H31: =TRUE() -> TRUE | I31: =FALSE() -> FALSE | J31: 1 | K31: https://meetblume.com/products/clear-skin-kit-3 | L31: 43.2
A32: Meltdown Daily Balancing Gel Cleanser | B32: blume-box | C32: Skin Care | D32: 32 | E32: 32 | G32: =FALSE() -> FALSE | H32: =TRUE() -> TRUE | I32: =FALSE() -> FALSE | J32: 1 | K32: https://meetblume.com/products/meltdown-gel-cleanser-made-with-salicylic-acid
A33: Blume Babies: Travel Size Kit | B33: Blume | C33: Bundle | D33: 29.4 | E33: 29.4 | F33: 56 | G33: =TRUE() -> TRUE | H33: =TRUE() -> TRUE | I33: =FALSE() -> FALSE | J33: 1 | K33: https://meetblume.com/products/blume-babies | L33: 47.5
A34: Treat & Hydrate Kit | B34: Blume | C34: Bundle | D34: 45 | E34: 45 | F34: 58 | G34: =TRUE() -> TRUE | H34: =TRUE() -> TRUE | I34: =FALSE() -> FALSE | J34: 1 | K34: https://meetblume.com/products/treat-hydrate-kit | L34: 22.4
A35: Meltdown Gel Cream with Ceramides | B35: blume-box | C35: Skin Care | D35: 28 | E35: 28 | G35: =FALSE() -> FALSE | H35: =TRUE() -> TRUE | I35: =FALSE() -> FALSE | J35: 1 | K35: https://meetblume.com/products/meltdown-gel-cream-for-acne-prone-skin

Sheet Markdown Exposure Model
A1: Blume — Markdown & Stockout Exposure Model
A2: Source: live Shopify catalog snapshot, 34 SKUs (see Data tab)
A4: ASSUMPTIONS (editable inputs — blue cells)
A5: Estimated avg units sold per SKU per month | B5: 30 | D5: Adjust to your assumption — drives all revenue-impact figures below
A6: Inventory holding cost rate (annual, % of stock value) | B6: 0.22 | D6: Industry standard range 20-25% — used for stockout-related carrying cost
A7: Benchmark on-sale rate (blume-box vendor line, Query 7) | B7: 0.238 | D7: Used as the 'healthy' on-sale rate target for the Blume bundle line
A9: CATALOG SNAPSHOT (from Data tab — Query-derived)
A10: Total SKUs in catalog | B10: =COUNTA(Data!A2:A35) -> 34
A11: Total catalog value (sum of price_min) | B11: =SUM(Data!D2:D35) -> 2392.6
A12: Average price per SKU | B12: =AVERAGE(Data!D2:D35) -> 70.370588
A13: SKUs on sale (all vendors) | B13: =COUNTIF(Data!G2:G35,TRUE()) -> 16
A14: SKUs fully out of stock | B14: =COUNTIF(Data!I2:I35,TRUE()) -> 5
A16: VENDOR-LINE COMPARISON (Query 7 finding)
B17: Blume (bundles) | C17: blume-box
A18: Total SKUs | B18: =COUNTIF(Data!B2:B35,"Blume") -> 13 | C18: =COUNTIF(Data!B2:B35,"blume-box") -> 21
A19: SKUs on sale | B19: =COUNTIFS(Data!B2:B35,"Blume",Data!G2:G35,TRUE()) -> 11 | C19: =COUNTIFS(Data!B2:B35,"blume-box",Data!G2:G35,TRUE()) -> 5
A20: On-sale rate | B20: =B19/B18 -> 0.84615385 | C20: =C19/C18 -> 0.23809524
A21: Avg price | B21: =AVERAGEIF(Data!B2:B35,"Blume",Data!D2:D35) -> 88.861538 | C21: =AVERAGEIF(Data!B2:B35,"blume-box",Data!D2:D35) -> 58.92381
A22: Avg discount % on on-sale SKUs | B22: =AVERAGEIFS(Data!L2:L35,Data!B2:B35,"Blume",Data!G2:G35,TRUE())/100 -> 0.28845455 | C22: =AVERAGEIFS(Data!L2:L35,Data!B2:B35,"blume-box",Data!G2:G35,TRUE())/100 -> 0.689
A24: SCENARIO — IF BLUME LINE'S ON-SALE RATE MATCHED THE BENCHMARK
A25: Excess SKUs currently on sale vs benchmark | B25: =MAX(0,B19-ROUND(B18*B7,0)) -> 8
A26: Avg discount amount per excess SKU ($) | B26: =B22*B21 -> 25.632515
A27: Monthly revenue recoverable (excess SKUs × discount $ × units/mo) | B27: =B25*B26*B5 -> 6151.8035
A28: Annualized revenue recoverable | B28: =B27*12 -> 73821.642
A30: STOCKOUT EXPOSURE (Query 4 finding)
A31: Bundle SKUs out of stock (Query 4: 3 of 11) | B31: 3
A32: Avg bundle price | B32: =AVERAGEIF(Data!C2:C35,"Bundle",Data!D2:D35) -> 56.381818
A33: Estimated monthly revenue lost to OOS bundles | B33: =B31*B32*B5 -> 5074.3636
A34: Annualized revenue lost to OOS bundles | B34: =B33*12 -> 60892.364
A36: Note: 'units sold per month' (B5) is an assumption since the dataset is a point-in-time catalog snapshot with no transaction history. Change B5 to stress-test the model.
